 <Application>
 
<Header>

  <Version val="14100.00"/>

  <WithIsn val="Y"/>

  <Exe comp="-1"/>

  <LastIsn val="3"/>

  <LastIsnFolder val="0"/>

</Header>

<DataRepositoryProperties/>
 <DataSourceRepository>
  <DataObjects>
 
<DataObject PhysicalName="testtable" Resident="N" UniqueISNConvState="12" data_source="SQLite Database" id="2" name="testtable" offset="228" length="2154"/> 
<DataObject PhysicalName="testtable" Resident="N" UniqueISNConvState="12" data_source="SQLite Database" id="3" name="table2" offset="2383" length="2151"/>  </DataObjects>
 </DataSourceRepository>
 <LastModified val="31088043160278729"/>  </Application>
